{
    "pagination": {
        "count": 19
    },
    "request": {
        "bioguideId": "b001279",
        "contentType": "application/json",
        "format": "json"
    },
    "sponsoredLegislation": [
        {
            "amendmentNumber": "602",
            "congress": 113,
            "introducedDate": "2014-03-26",
            "latestAction": {
                "actionDate": "2014-03-26",
                "actionTime": "15:54:41",
                "text": "On agreeing to the Barber amendment (A002) Agreed to by voice vote. "
            },
            "type": null,
            "url": "https://api.congress.gov/v3/amendment/113/hamdt/602?format=json"
        },
        {
            "amendmentNumber": "434",
            "congress": 113,
            "introducedDate": "2013-07-30",
            "latestAction": {
                "actionDate": "2013-07-30",
                "actionTime": "21:01:16",
                "text": "Amendment (A018) offered by Mr. Barber. (consideration: CR H5154-5155; text: CR H5154)"
            },
            "type": null,
            "url": "https://api.congress.gov/v3/amendment/113/hamdt/434?format=json"
        },
        {
            "congress": 113,
            "introducedDate": "2014-11-20",
            "latestAction": {
                "actionDate": "2014-11-20",
                "text": "Referred to the House Committee on Armed Services."
            },
            "number": "5760",
            "policyArea": {
                "name": "Armed Forces and National Security"
            },
            "title": "Funeral Honors for World War II Veterans Act",
            "type": "HR",
            "url": "https://api.congress.gov/v3/bill/113/hr/5760?format=json"
        },
        {
            "congress": 113,
            "introducedDate": "2014-09-18",
            "latestAction": {
                "actionDate": "2014-09-18",
                "text": "Referred to the House Committee on Ways and Means."
            },
            "number": "5552",
            "policyArea": {
                "name": "Government Operations and Politics"
            },
            "title": "To designate the United States Customs and Border Protection Port of Entry located at First Street and Pan American Avenue in Douglas, Arizona, as the \"Raul Hector Castro Port of Entry\".",
            "type": "HR",
            "url": "https://api.congress.gov/v3/bill/113/hr/5552?format=json"
        },
        {
            "congress": 113,
            "introducedDate": "2014-07-30",
            "latestAction": {
                "actionDate": "2014-08-15",
                "text": "Referred to the Subcommittee on Economic Opportunity."
            },
            "number": "5273",
            "policyArea": {
                "name": "Armed Forces and National Security"
            },
            "title": "Post-9/11 Veterans Education Fairness Act",
            "type": "HR",
            "url": "https://api.congress.gov/v3/bill/113/hr/5273?format=json"
        },
        {
            "congress": 113,
            "introducedDate": "2014-05-06",
            "latestAction": {
                "actionDate": "2014-07-21",
                "text": "Referred to the Subcommittee on Crime, Terrorism, Homeland Security, and Investigations."
            },
            "number": "4574",
            "policyArea": {
                "name": "Health"
            },
            "title": "Strengthening Mental Health in Our Communities Act of 2014",
            "type": "HR",
            "url": "https://api.congress.gov/v3/bill/113/hr/4574?format=json"
        },
        {
            "congress": 113,
            "introducedDate": "2014-04-02",
            "latestAction": {
                "actionDate": "2014-04-02",
                "text": "Referred to the House Committee on Oversight and Government Reform."
            },
            "number": "4375",
            "policyArea": {
                "name": "Government Operations and Politics"
            },
            "title": "To designate the facility of the United States Postal Service located at 100 North Taylor Lane in Patagonia, Arizona, as the \"Jim Kolbe Post Office\".",
            "type": "HR",
            "url": "https://api.congress.gov/v3/bill/113/hr/4375?format=json"
        },
        {
            "congress": 113,
            "introducedDate": "2014-03-18",
            "latestAction": {
                "actionDate": "2014-03-18",
                "text": "Referred to the House Committee on Appropriations."
            },
            "number": "4274",
            "policyArea": {
                "name": "Armed Forces and National Security"
            },
            "title": "To amend the Honoring the Families of Fallen Soldiers Act to provide a permanent appropriation of funds for the payment of death gratuities for survivors of deceased members of the uniformed services in event of any future period of lapsed appropriations.",
            "type": "HR",
            "url": "https://api.congress.gov/v3/bill/113/hr/4274?format=json"
        },
        {
            "congress": 113,
            "introducedDate": "2014-02-25",
            "latestAction": {
                "actionDate": "2014-02-28",
                "text": "Referred to the Subcommittee on Health."
            },
            "number": "4075",
            "policyArea": {
                "name": "Health"
            },
            "title": "SPRINT Act",
            "type": "HR",
            "url": "https://api.congress.gov/v3/bill/113/hr/4075?format=json"
        },
        {
            "congress": 113,
            "introducedDate": "2014-01-10",
            "latestAction": {
                "actionDate": "2014-01-17",
                "text": "Referred to the Subcommittee on Health."
            },
            "number": "3847",
            "policyArea": {
                "name": "Health"
            },
            "title": "CARE Act of 2013",
            "type": "HR",
            "url": "https://api.congress.gov/v3/bill/113/hr/3847?format=json"
        },
        {
            "congress": 113,
            "introducedDate": "2013-10-08",
            "latestAction": {
                "actionDate": "2013-10-08",
                "text": "Referred to the House Committee on Appropriations."
            },
            "number": "3274",
            "policyArea": {
                "name": "Armed Forces and National Security"
            },
            "title": "Fallen Heroes and Families Assistance Act",
            "type": "HR",
            "url": "https://api.congress.gov/v3/bill/113/hr/3274?format=json"
        },
        {
            "congress": 113,
            "introducedDate": "2013-09-17",
            "latestAction": {
                "actionDate": "2013-09-17",
                "text": "Referred to the House Committee on Ways and Means."
            },
            "number": "3114",
            "policyArea": {
                "name": "Taxation"
            },
            "title": "Helping Families and Seniors Save on Health Care Act of 2013",
            "type": "HR",
            "url": "https://api.congress.gov/v3/bill/113/hr/3114?format=json"
        },
        {
            "congress": 113,
            "introducedDate": "2013-06-18",
            "latestAction": {
                "actionDate": "2013-07-01",
                "text": "Referred to the Subcommittee on Health."
            },
            "number": "2412",
            "policyArea": {
                "name": "Armed Forces and National Security"
            },
            "title": "Veterans Health Access Act",
            "type": "HR",
            "url": "https://api.congress.gov/v3/bill/113/hr/2412?format=json"
        },
        {
            "congress": 113,
            "introducedDate": "2013-04-24",
            "latestAction": {
                "actionDate": "2013-07-09",
                "text": "Subcommittee Hearings Held."
            },
            "number": "1702",
            "policyArea": {
                "name": "Armed Forces and National Security"
            },
            "title": "Veterans Transportation Service Act",
            "type": "HR",
            "url": "https://api.congress.gov/v3/bill/113/hr/1702?format=json"
        },
        {
            "congress": 113,
            "introducedDate": "2013-04-10",
            "latestAction": {
                "actionDate": "2013-04-10",
                "text": "Referred to the Committee on House Administration, and in addition to the Committee on Oversight and Government Reform, for a period to be subsequently determined by the Speaker, in each case for consideration of such provisions as fall within the jurisdiction of the committee concerned."
            },
            "number": "1467",
            "policyArea": {
                "name": "Congress"
            },
            "title": "Pay Cut for Congress Act",
            "type": "HR",
            "url": "https://api.congress.gov/v3/bill/113/hr/1467?format=json"
        },
        {
            "congress": 113,
            "introducedDate": "2013-01-15",
            "latestAction": {
                "actionDate": "2013-01-18",
                "text": "Referred to the Subcommittee on Health."
            },
            "number": "274",
            "policyArea": {
                "name": "Health"
            },
            "title": "Mental Health First Act of 2013",
            "type": "HR",
            "url": "https://api.congress.gov/v3/bill/113/hr/274?format=json"
        },
        {
            "congress": 113,
            "introducedDate": "2014-09-18",
            "latestAction": {
                "actionDate": "2014-09-18",
                "text": "Referred to the House Committee on Armed Services."
            },
            "number": "736",
            "policyArea": {
                "name": "Armed Forces and National Security"
            },
            "title": "Affirming the importance of the Electronic Proving Ground at Fort Huachuca, Arizona, to the United States Armed Forces and national security on its 60th anniversary.",
            "type": "HRES",
            "url": "https://api.congress.gov/v3/bill/113/hres/736?format=json"
        },
        {
            "congress": 113,
            "introducedDate": "2014-03-06",
            "latestAction": {
                "actionDate": "2014-03-06",
                "text": "Referred to the House Committee on Education and the Workforce."
            },
            "number": "507",
            "policyArea": {
                "name": "Labor and Employment"
            },
            "title": "Expressing the sense of the House of Representatives in support of a women's economic bill of rights.",
            "type": "HRES",
            "url": "https://api.congress.gov/v3/bill/113/hres/507?format=json"
        },
        {
            "congress": 112,
            "introducedDate": "2012-09-13",
            "latestAction": {
                "actionDate": "2012-10-05",
                "text": "Referred to the Subcommittee on Military Personnel."
            },
            "number": "6393",
            "policyArea": {
                "name": "Armed Forces and National Security"
            },
            "title": "Veterans Health Access Act",
            "type": "HR",
            "url": "https://api.congress.gov/v3/bill/112/hr/6393?format=json"
        }
    ]
}