{
    "pagination": {
        "count": 27
    },
    "request": {
        "bioguideId": "k000400",
        "contentType": "application/json",
        "format": "json"
    },
    "sponsoredLegislation": [
        {
            "congress": 118,
            "introducedDate": "2024-07-08",
            "latestAction": {
                "actionDate": "2024-07-08",
                "text": "Referred to the House Committee on Education and the Workforce."
            },
            "number": "8943",
            "policyArea": {
                "name": null
            },
            "title": "To direct the Secretary of Education to carry out a grant program to support arts education at minority-serving institutions of higher education.",
            "type": "HR",
            "url": "https://api.congress.gov/v3/bill/118/hr/8943?format=json"
        },
        {
            "congress": 118,
            "introducedDate": "2024-06-18",
            "latestAction": {
                "actionDate": "2024-06-18",
                "text": "Referred to the House Committee on the Judiciary."
            },
            "number": "1309",
            "policyArea": {
                "name": "Civil Rights and Liberties, Minority Issues"
            },
            "title": "Continuing the promise of Juneteenth: honoring, preserving, and investing in freedmen's settlements.",
            "type": "HRES",
            "url": "https://api.congress.gov/v3/bill/118/hres/1309?format=json"
        },
        {
            "congress": 118,
            "introducedDate": "2024-06-12",
            "latestAction": {
                "actionDate": "2024-06-12",
                "text": "Referred to the House Committee on Ways and Means."
            },
            "number": "8713",
            "policyArea": {
                "name": null
            },
            "title": "To amend parts B and E of title IV of the Social Security Act to remove barriers and encourage kinship guardianship, foster, or adoptive placements for children who cannot be safely cared for in their own homes, and for other purposes.",
            "type": "HR",
            "url": "https://api.congress.gov/v3/bill/118/hr/8713?format=json"
        },
        {
            "congress": 118,
            "introducedDate": "2024-05-22",
            "latestAction": {
                "actionDate": "2024-05-22",
                "text": "Referred to the Subcommittee on Border Security and Enforcement."
            },
            "number": "8502",
            "policyArea": {
                "name": null
            },
            "title": "Children\u2019s Safe Welcome Act of 2024",
            "type": "HR",
            "url": "https://api.congress.gov/v3/bill/118/hr/8502?format=json"
        },
        {
            "congress": 118,
            "introducedDate": "2024-05-07",
            "latestAction": {
                "actionDate": "2024-05-07",
                "text": "Referred to the House Committee on Education and the Workforce."
            },
            "number": "8273",
            "policyArea": {
                "name": null
            },
            "title": "Higher Education Access and Success for Homeless and Foster Youth Act of 2024",
            "type": "HR",
            "url": "https://api.congress.gov/v3/bill/118/hr/8273?format=json"
        },
        {
            "congress": 118,
            "introducedDate": "2024-04-20",
            "latestAction": {
                "actionDate": "2024-04-20",
                "text": "Referred to the Committee on Foreign Affairs, and in addition to the Committee on Energy and Commerce, for a period to be subsequently determined by the Speaker, in each case for consideration of such provisions as fall within the jurisdiction of the committee concerned."
            },
            "number": "1164",
            "policyArea": {
                "name": null
            },
            "title": "Acknowledging the particular threat climate change poses to a secure and sustainable future for all children and the important stake children have in a healthy planet.",
            "type": "HRES",
            "url": "https://api.congress.gov/v3/bill/118/hres/1164?format=json"
        },
        {
            "congress": 118,
            "introducedDate": "2023-12-19",
            "latestAction": {
                "actionDate": "2023-12-19",
                "text": "Referred to the House Committee on Natural Resources."
            },
            "number": "6859",
            "policyArea": {
                "name": "Native Americans"
            },
            "title": "Gabrielino/Tongva Nation Recognition Act of 2023",
            "type": "HR",
            "url": "https://api.congress.gov/v3/bill/118/hr/6859?format=json"
        },
        {
            "congress": 118,
            "introducedDate": "2023-11-28",
            "latestAction": {
                "actionDate": "2023-12-01",
                "text": "Referred to the Subcommittee on Health."
            },
            "number": "6484",
            "policyArea": {
                "name": "Health"
            },
            "title": "Expanded Coverage for Former Foster Youth Act",
            "type": "HR",
            "url": "https://api.congress.gov/v3/bill/118/hr/6484?format=json"
        },
        {
            "congress": 118,
            "introducedDate": "2023-10-26",
            "latestAction": {
                "actionDate": "2023-11-07",
                "text": "Ordered to be Reported by Voice Vote."
            },
            "number": "6087",
            "policyArea": {
                "name": "International Affairs"
            },
            "title": "Young African Leaders Initiative Act of 2023",
            "type": "HR",
            "url": "https://api.congress.gov/v3/bill/118/hr/6087?format=json"
        },
        {
            "congress": 118,
            "introducedDate": "2023-10-25",
            "latestAction": {
                "actionDate": "2023-10-25",
                "text": "Referred to the House Committee on Foreign Affairs."
            },
            "number": "6054",
            "policyArea": {
                "name": "International Affairs"
            },
            "title": "Represent America Abroad Act of 2023",
            "type": "HR",
            "url": "https://api.congress.gov/v3/bill/118/hr/6054?format=json"
        },
        {
            "congress": 118,
            "introducedDate": "2023-10-18",
            "latestAction": {
                "actionDate": "2023-10-25",
                "text": "Referred to the House Committee on the Judiciary."
            },
            "number": "5982",
            "policyArea": {
                "name": "Immigration"
            },
            "title": "GRATEFUL Act",
            "type": "HR",
            "url": "https://api.congress.gov/v3/bill/118/hr/5982?format=json"
        },
        {
            "congress": 118,
            "introducedDate": "2023-09-18",
            "latestAction": {
                "actionDate": "2023-09-18",
                "text": "Referred to the House Committee on Ways and Means."
            },
            "number": "694",
            "policyArea": {
                "name": "Families"
            },
            "title": "Expressing support for the designation of September 2023 as \"National Kinship Care Month\".",
            "type": "HRES",
            "url": "https://api.congress.gov/v3/bill/118/hres/694?format=json"
        },
        {
            "congress": 118,
            "introducedDate": "2023-07-26",
            "latestAction": {
                "actionDate": "2023-07-26",
                "text": "Referred to the House Committee on Education and the Workforce."
            },
            "number": "618",
            "policyArea": {
                "name": "Arts, Culture, Religion"
            },
            "title": "Recognizing August 11, 2023, as the 50th anniversary of hip-hop.",
            "type": "HRES",
            "url": "https://api.congress.gov/v3/bill/118/hres/618?format=json"
        },
        {
            "congress": 118,
            "introducedDate": "2023-07-26",
            "latestAction": {
                "actionDate": "2023-07-26",
                "text": "Referred to the House Committee on Natural Resources."
            },
            "number": "4916",
            "policyArea": {
                "name": "Energy"
            },
            "title": "Comprehensive Legislation for Expanding and Advancing Nonrestrictive Energy Act",
            "type": "HR",
            "url": "https://api.congress.gov/v3/bill/118/hr/4916?format=json"
        },
        {
            "congress": 118,
            "introducedDate": "2023-07-20",
            "latestAction": {
                "actionDate": "2023-07-20",
                "text": "Referred to the Committee on the Judiciary, and in addition to the Committee on Ways and Means, for a period to be subsequently determined by the Speaker, in each case for consideration of such provisions as fall within the jurisdiction of the committee concerned."
            },
            "number": "4792",
            "policyArea": {
                "name": "Crime and Law Enforcement"
            },
            "title": "Childhood Offenders Rehabilitation and Safety Act of 2023",
            "type": "HR",
            "url": "https://api.congress.gov/v3/bill/118/hr/4792?format=json"
        },
        {
            "congress": 118,
            "introducedDate": "2023-07-11",
            "latestAction": {
                "actionDate": "2023-07-26",
                "text": "Ordered to be Reported in the Nature of a Substitute (Amended) by Voice Vote."
            },
            "number": "578",
            "policyArea": {
                "name": "International Affairs"
            },
            "title": "Calling for the immediate release of Eyvin Hernandez, a United States citizen and Los Angeles County public defender, who was wrongfully detained by the Venezuelan regime in March 2022.",
            "type": "HRES",
            "url": "https://api.congress.gov/v3/bill/118/hres/578?format=json"
        },
        {
            "congress": 118,
            "introducedDate": "2023-05-25",
            "latestAction": {
                "actionDate": "2023-05-26",
                "text": "Referred to the Subcommittee on Health."
            },
            "number": "3701",
            "policyArea": {
                "name": "Health"
            },
            "title": "Foster Youth Dental Act of 2023",
            "type": "HR",
            "url": "https://api.congress.gov/v3/bill/118/hr/3701?format=json"
        },
        {
            "congress": 118,
            "introducedDate": "2023-05-05",
            "latestAction": {
                "actionDate": "2023-05-05",
                "text": "Referred to the House Committee on the Judiciary."
            },
            "number": "366",
            "policyArea": {
                "name": "Crime and Law Enforcement"
            },
            "title": "Commemorating the 31st anniversary of the 1992 Los Angeles riots.",
            "type": "HRES",
            "url": "https://api.congress.gov/v3/bill/118/hres/366?format=json"
        },
        {
            "congress": 118,
            "introducedDate": "2023-05-02",
            "latestAction": {
                "actionDate": "2023-05-23",
                "text": "Sponsor introductory remarks on measure. (CR H2508)"
            },
            "number": "349",
            "policyArea": {
                "name": "Families"
            },
            "title": "Recognizing National Foster Care Month as an opportunity to raise awareness about the challenges of children in the foster care system and encouraging Congress to implement policy to improve the lives of children in, or at risk of entering, the foster care system.",
            "type": "HRES",
            "url": "https://api.congress.gov/v3/bill/118/hres/349?format=json"
        },
        {
            "congress": 118,
            "introducedDate": "2023-04-27",
            "latestAction": {
                "actionDate": "2023-04-28",
                "text": "Referred to the Subcommittee on Health."
            },
            "number": "2954",
            "policyArea": {
                "name": "Crime and Law Enforcement"
            },
            "title": "Women in Criminal Justice Reform Act",
            "type": "HR",
            "url": "https://api.congress.gov/v3/bill/118/hr/2954?format=json"
        },
        {
            "congress": 118,
            "introducedDate": "2023-04-20",
            "latestAction": {
                "actionDate": "2023-04-20",
                "text": "Referred to the House Committee on Ways and Means."
            },
            "number": "2762",
            "policyArea": {
                "name": "Native Americans"
            },
            "title": "Tribal Family Fairness Act",
            "type": "HR",
            "url": "https://api.congress.gov/v3/bill/118/hr/2762?format=json"
        },
        {
            "congress": 118,
            "introducedDate": "2023-04-13",
            "latestAction": {
                "actionDate": "2023-04-17",
                "text": "Sponsor introductory remarks on measure. (CR H1749-1750)"
            },
            "number": "292",
            "policyArea": {
                "name": "Civil Rights and Liberties, Minority Issues"
            },
            "title": "Condemning the expulsion of two Black, duly elected Tennessee Representatives as a blatant act of racism and an attack on the democracy of the United States and observing that the Tennessee House of Representatives preferred to take this action of expulsion rather than to act on gun control measures to protect children.",
            "type": "HRES",
            "url": "https://api.congress.gov/v3/bill/118/hres/292?format=json"
        },
        {
            "congress": 118,
            "introducedDate": "2023-03-28",
            "latestAction": {
                "actionDate": "2023-03-28",
                "text": "Referred to the House Committee on Foreign Affairs."
            },
            "number": "261",
            "policyArea": {
                "name": "International Affairs"
            },
            "title": "Reaffirming the importance of diplomacy and development in United States-African Union relations, promoting strategic partnerships and shared objectives between the United States and the African Union, and expressing strong support for the successful implementation of the African Continental Free Trade Area.",
            "type": "HRES",
            "url": "https://api.congress.gov/v3/bill/118/hres/261?format=json"
        },
        {
            "congress": 118,
            "introducedDate": "2023-02-10",
            "latestAction": {
                "actionDate": "2023-02-10",
                "text": "Referred to the House Committee on the Judiciary."
            },
            "number": "981",
            "policyArea": {
                "name": "Crime and Law Enforcement"
            },
            "title": "One Stop Shop Community Reentry Program Act of 2023",
            "type": "HR",
            "url": "https://api.congress.gov/v3/bill/118/hr/981?format=json"
        },
        {
            "congress": 118,
            "introducedDate": "2023-02-10",
            "latestAction": {
                "actionDate": "2023-02-10",
                "text": "Referred to the Committee on the Judiciary, and in addition to the Committee on the Budget, for a period to be subsequently determined by the Speaker, in each case for consideration of such provisions as fall within the jurisdiction of the committee concerned."
            },
            "number": "982",
            "policyArea": {
                "name": "Crime and Law Enforcement"
            },
            "title": "Pregnant Women in Custody Act",
            "type": "HR",
            "url": "https://api.congress.gov/v3/bill/118/hr/982?format=json"
        },
        {
            "congress": 118,
            "introducedDate": "2023-01-13",
            "latestAction": {
                "actionDate": "2023-01-13",
                "text": "Referred to the House Committee on Education and the Workforce."
            },
            "number": "37",
            "policyArea": {
                "name": "Education"
            },
            "title": "Honoring Zeta Phi Beta Sorority, Inc., on reaching the historic milestone of 103 years of scholarship, service, sisterhood, and finer womanhood.",
            "type": "HRES",
            "url": "https://api.congress.gov/v3/bill/118/hres/37?format=json"
        },
        {
            "congress": 118,
            "introducedDate": "2024-03-13",
            "latestAction": {
                "actionDate": "2024-03-13",
                "text": "Referred to the House Committee on Ways and Means."
            },
            "number": "7664",
            "policyArea": {
                "name": "Families"
            },
            "title": "21st Century Children and Families Act",
            "type": "HR",
            "url": "https://api.congress.gov/v3/bill/118/hr/7664?format=json"
        }
    ]
}